odoo/addons/l10n_br_crm_cnpj_search/README.rst
odoo/addons/l10n_br_crm_cnpj_search/__init__.py
odoo/addons/l10n_br_crm_cnpj_search/__manifest__.py
odoo/addons/l10n_br_crm_cnpj_search/i18n/l10n_br_crm_cnpj_search.pot
odoo/addons/l10n_br_crm_cnpj_search/models/__init__.py
odoo/addons/l10n_br_crm_cnpj_search/models/crm_lead.py
odoo/addons/l10n_br_crm_cnpj_search/readme/CONFIGURE.md
odoo/addons/l10n_br_crm_cnpj_search/readme/CONTRIBUTORS.md
odoo/addons/l10n_br_crm_cnpj_search/readme/DESCRIPTION.md
odoo/addons/l10n_br_crm_cnpj_search/readme/INSTALL.md
odoo/addons/l10n_br_crm_cnpj_search/readme/USAGE.md
odoo/addons/l10n_br_crm_cnpj_search/static/description/icon.png
odoo/addons/l10n_br_crm_cnpj_search/static/description/index.html
odoo/addons/l10n_br_crm_cnpj_search/tests/__init__.py
odoo/addons/l10n_br_crm_cnpj_search/tests/test_receitaws.py
odoo/addons/l10n_br_crm_cnpj_search/views/crm_lead_form.xml
odoo/addons/l10n_br_crm_cnpj_search/wizard/__init__.py
odoo/addons/l10n_br_crm_cnpj_search/wizard/partner_cnpj_search_wizard.py
odoo_addon_l10n_br_crm_cnpj_search-16.0.5.1.0.dist-info/METADATA
odoo_addon_l10n_br_crm_cnpj_search-16.0.5.1.0.dist-info/WHEEL
odoo_addon_l10n_br_crm_cnpj_search-16.0.5.1.0.dist-info/top_level.txt
odoo_addon_l10n_br_crm_cnpj_search-16.0.5.1.0.dist-info/RECORD
