Metadata-Version: 2.1
Name: odoo-addon-l10n_br_crm_cnpj_search
Version: 16.0.5.1.0
Requires-Python: >=3.10
Requires-Dist: odoo-addon-l10n_br_cnpj_search>=16.0dev,<16.1dev
Requires-Dist: odoo-addon-l10n_br_crm>=16.0dev,<16.1dev
Requires-Dist: odoo>=16.0a,<16.1dev
Summary: CNPJ search in CRM Lead
Home-page: https://github.com/OCA/l10n-brazil
License: AGPL-3
Author: KMEE,Odoo Community Association (OCA)
Author-email: support@odoo-community.org
Classifier: Programming Language :: Python
Classifier: Framework :: Odoo
Classifier: Framework :: Odoo :: 16.0
Classifier: License :: OSI Approved :: GNU Affero General Public License v3
